raven_sqs_proxy/__about__.py
raven_sqs_proxy/__init__.py
raven_sqs_proxy/sqsproxy.py
raven_sqs_proxy/tests/__init__.py
raven_sqs_proxy/tests/conftest.py
raven_sqs_proxy/tests/test_sqsproxy.py
raven_sqs_proxy-0.1.0.dist-info/DESCRIPTION.rst
raven_sqs_proxy-0.1.0.dist-info/METADATA
raven_sqs_proxy-0.1.0.dist-info/RECORD
raven_sqs_proxy-0.1.0.dist-info/WHEEL
raven_sqs_proxy-0.1.0.dist-info/entry_points.txt
raven_sqs_proxy-0.1.0.dist-info/metadata.json
raven_sqs_proxy-0.1.0.dist-info/top_level.txt
